meeting_noter_models/__init__.py
meeting_noter_models/model/config.json
meeting_noter_models/model/model.bin
meeting_noter_models/model/tokenizer.json
meeting_noter_models/model/vocabulary.txt
meeting_noter_models-0.1.0.dist-info/METADATA
meeting_noter_models-0.1.0.dist-info/WHEEL
meeting_noter_models-0.1.0.dist-info/top_level.txt
meeting_noter_models-0.1.0.dist-info/RECORD
