Metadata-Version: 2.4
Name: meeting-noter-models
Version: 0.1.0
Summary: Bundled Whisper model for meeting-noter offline transcription
Author: Victor
License: MIT
Project-URL: Homepage, https://github.com/tech4vision/meeting-noter
Project-URL: Repository, https://github.com/tech4vision/meeting-noter
Keywords: meeting-noter,whisper,model,offline
Classifier: Development Status :: 3 - Alpha
Classifier: License :: OSI Approved :: MIT License
Classifier: Operating System :: OS Independent
Classifier: Programming Language :: Python :: 3
Requires-Python: >=3.9
